{"file":"mall.png","frames":{
"ui_mall_WordsShadow_png":{"x":1,"y":1,"w":263,"h":179,"offX":1,"offY":0,"sourceW":264,"sourceH":179},
"ui_mail_taiyanglunpanlibao_png":{"x":792,"y":1,"w":160,"h":154,"offX":9,"offY":16,"sourceW":180,"sourceH":180},
"ui_mall_BoardBuyNum_png":{"x":1,"y":616,"w":138,"h":99,"offX":0,"offY":0,"sourceW":138,"sourceH":99},
"ui_mall_BoardCurrentGemstone_png":{"x":1,"y":558,"w":244,"h":42,"offX":0,"offY":0,"sourceW":244,"sourceH":42},
"ui_mall_BoardDiscound_png":{"x":970,"y":765,"w":52,"h":59,"offX":0,"offY":0,"sourceW":52,"sourceH":59},
"ui_mall_BoardGes_png":{"x":812,"y":308,"w":61,"h":416,"offX":0,"offY":0,"sourceW":61,"sourceH":416},
"ui_mall_BoardMallItem_png":{"x":264,"y":182,"w":365,"h":124,"offX":4,"offY":4,"sourceW":373,"sourceH":132},
"ui_mall_BoardMallItemInfo_png":{"x":88,"y":839,"w":220,"h":28,"offX":0,"offY":0,"sourceW":220,"sourceH":28},
"ui_mall_BoardMallItemSel_png":{"x":631,"y":182,"w":365,"h":124,"offX":4,"offY":4,"sourceW":373,"sourceH":132},
"ui_mall_BoardMallRes_png":{"x":1,"y":423,"w":586,"h":39,"offX":0,"offY":0,"sourceW":586,"sourceH":39},
"ui_mall_BoardMallResTip_png":{"x":1,"y":726,"w":428,"h":42,"offX":0,"offY":0,"sourceW":428,"sourceH":42},
"ui_mall_BoardMallTip_png":{"x":1,"y":530,"w":450,"h":26,"offX":0,"offY":0,"sourceW":450,"sourceH":26},
"ui_mall_BoardSellMax_png":{"x":264,"y":308,"w":278,"h":113,"offX":0,"offY":0,"sourceW":278,"sourceH":113},
"ui_mall_ButtonGemstonBuyDis_png":{"x":529,"y":1,"w":261,"h":179,"offX":0,"offY":0,"sourceW":261,"sourceH":179},
"ui_mall_ButtonGemstonBuyNor_png":{"x":266,"y":1,"w":261,"h":179,"offX":0,"offY":0,"sourceW":261,"sourceH":179},
"ui_mall_ButtonGemstonBuySel_png":{"x":1,"y":182,"w":261,"h":179,"offX":0,"offY":0,"sourceW":261,"sourceH":179},
"ui_mall_ButtonMallArenaNor_png":{"x":98,"y":869,"w":137,"h":44,"offX":0,"offY":0,"sourceW":137,"sourceH":53},
"ui_mall_ButtonMallArenaSel_png":{"x":455,"y":962,"w":137,"h":50,"offX":0,"offY":0,"sourceW":137,"sourceH":53},
"ui_mall_ButtonMallBuyNor_png":{"x":305,"y":962,"w":148,"h":49,"offX":0,"offY":0,"sourceW":148,"sourceH":49},
"ui_mall_ButtonMallBuySel_png":{"x":155,"y":962,"w":148,"h":49,"offX":0,"offY":0,"sourceW":148,"sourceH":49},
"ui_mall_ButtonMallChargeNor_png":{"x":1,"y":962,"w":152,"h":49,"offX":5,"offY":5,"sourceW":161,"sourceH":62},
"ui_mall_ButtonMallChargeSel_png":{"x":1,"y":363,"w":152,"h":55,"offX":5,"offY":4,"sourceW":161,"sourceH":62},
"ui_mall_ButtonMallGemstoneNor_png":{"x":536,"y":776,"w":155,"h":41,"offX":6,"offY":9,"sourceW":169,"sourceH":67},
"ui_mall_ButtonMallGemstoneSel_png":{"x":453,"y":530,"w":156,"h":61,"offX":5,"offY":6,"sourceW":169,"sourceH":67},
"ui_mall_ButtonMallGiftNor_png":{"x":835,"y":843,"w":133,"h":38,"offX":3,"offY":3,"sourceW":139,"sourceH":52},
"ui_mall_ButtonMallGiftSel_png":{"x":227,"y":770,"w":133,"h":49,"offX":3,"offY":2,"sourceW":139,"sourceH":52},
"ui_mall_ButtonMallHonorNor_png":{"x":515,"y":916,"w":137,"h":44,"offX":0,"offY":0,"sourceW":137,"sourceH":53},
"ui_mall_ButtonMallHonorSel_png":{"x":872,"y":962,"w":137,"h":50,"offX":0,"offY":0,"sourceW":137,"sourceH":53},
"ui_mall_ButtonMallNor_png":{"x":237,"y":916,"w":137,"h":44,"offX":0,"offY":0,"sourceW":137,"sourceH":53},
"ui_mall_ButtonMallOverflowNor_png":{"x":362,"y":873,"w":155,"h":41,"offX":6,"offY":9,"sourceW":169,"sourceH":67},
"ui_mall_ButtonMallOverflowSel_png":{"x":433,"y":593,"w":155,"h":61,"offX":6,"offY":6,"sourceW":169,"sourceH":67},
"ui_mall_ButtonMallPrintNor_png":{"x":362,"y":787,"w":155,"h":41,"offX":6,"offY":9,"sourceW":169,"sourceH":67},
"ui_mall_ButtonMallPrintSel_png":{"x":276,"y":621,"w":155,"h":61,"offX":6,"offY":6,"sourceW":169,"sourceH":67},
"ui_mall_ButtonMallRushNor_png":{"x":589,"y":422,"w":81,"h":36,"offX":0,"offY":0,"sourceW":81,"sourceH":36},
"ui_mall_ButtonMallRushSel_png":{"x":519,"y":871,"w":81,"h":36,"offX":0,"offY":0,"sourceW":81,"sourceH":36},
"ui_mall_ButtonMallSel_png":{"x":88,"y":787,"w":137,"h":50,"offX":0,"offY":0,"sourceW":137,"sourceH":53},
"ui_mall_ButtonMallUnionNor_png":{"x":376,"y":916,"w":137,"h":44,"offX":0,"offY":0,"sourceW":137,"sourceH":53},
"ui_mall_ButtonMallUnionSel_png":{"x":733,"y":962,"w":137,"h":50,"offX":0,"offY":0,"sourceW":137,"sourceH":53},
"ui_mall_ButtonTavernMallNor_png":{"x":98,"y":916,"w":137,"h":44,"offX":0,"offY":0,"sourceW":137,"sourceH":53},
"ui_mall_ButtonTavernMallSel_png":{"x":594,"y":962,"w":137,"h":50,"offX":0,"offY":0,"sourceW":137,"sourceH":53},
"ui_mall_ButtonVipGiftNor_png":{"x":362,"y":830,"w":155,"h":41,"offX":6,"offY":9,"sourceW":169,"sourceH":67},
"ui_mall_ButtonVipGiftSel_png":{"x":276,"y":558,"w":155,"h":61,"offX":6,"offY":6,"sourceW":169,"sourceH":67},
"ui_mall_IconGemstone1_png":{"x":654,"y":819,"w":66,"h":50,"offX":60,"offY":64,"sourceW":180,"sourceH":180},
"ui_mall_IconGemstone2_png":{"x":155,"y":363,"w":80,"h":53,"offX":48,"offY":64,"sourceW":180,"sourceH":180},
"ui_mall_IconGemstone3_png":{"x":710,"y":422,"w":96,"h":67,"offX":41,"offY":63,"sourceW":180,"sourceH":180},
"ui_mall_IconGemstone4_png":{"x":875,"y":607,"w":137,"h":75,"offX":22,"offY":59,"sourceW":180,"sourceH":180},
"ui_mall_IconGemstone5_png":{"x":875,"y":684,"w":112,"h":79,"offX":34,"offY":59,"sourceW":180,"sourceH":180},
"ui_mall_IconGemstone6_png":{"x":141,"y":616,"w":133,"h":97,"offX":21,"offY":45,"sourceW":180,"sourceH":180},
"ui_mall_IconGemstone7_png":{"x":875,"y":308,"w":138,"h":117,"offX":17,"offY":27,"sourceW":180,"sourceH":180},
"ui_mall_IconGemstone8_png":{"x":641,"y":497,"w":153,"h":117,"offX":9,"offY":31,"sourceW":180,"sourceH":180},
"ui_mall_IconNew_png":{"x":725,"y":616,"w":81,"h":95,"offX":1,"offY":1,"sourceW":84,"sourceH":98},
"ui_mall_IconSoldOut_png":{"x":875,"y":427,"w":147,"h":94,"offX":0,"offY":0,"sourceW":148,"sourceH":94},
"ui_mall_Make_png":{"x":544,"y":308,"w":266,"h":112,"offX":1,"offY":1,"sourceW":268,"sourceH":116},
"ui_mall_OrnGemstoneMallTop_png":{"x":276,"y":684,"w":336,"h":27,"offX":0,"offY":0,"sourceW":336,"sourceH":27},
"ui_mall_OrnGemstoneMallTop1_png":{"x":1,"y":497,"w":638,"h":31,"offX":1,"offY":0,"sourceW":640,"sourceH":31},
"ui_mall_OrnMallTopB_png":{"x":1,"y":464,"w":707,"h":31,"offX":0,"offY":0,"sourceW":707,"sourceH":31},
"ui_mall_WordsBurGet_png":{"x":536,"y":713,"w":74,"h":56,"offX":0,"offY":0,"sourceW":74,"sourceH":56},
"ui_mall_WordsBuyNum_png":{"x":1,"y":874,"w":95,"h":75,"offX":0,"offY":0,"sourceW":95,"sourceH":75},
"ui_mall_WordsDayGet_png":{"x":433,"y":656,"w":97,"h":26,"offX":0,"offY":0,"sourceW":97,"sourceH":26},
"ui_mall_WordsGmestoneFirstSend_png":{"x":614,"y":616,"w":109,"h":78,"offX":0,"offY":0,"sourceW":109,"sourceH":78},
"ui_mall_WordsGmestoneFirstSendA_png":{"x":614,"y":696,"w":108,"h":78,"offX":1,"offY":0,"sourceW":109,"sourceH":78},
"ui_mall_WordsGmestoneFirstSendB_png":{"x":834,"y":884,"w":108,"h":76,"offX":0,"offY":1,"sourceW":109,"sourceH":77},
"ui_mall_WordsGmestoneFirstSendC_png":{"x":724,"y":884,"w":108,"h":76,"offX":0,"offY":1,"sourceW":109,"sourceH":77},
"ui_mall_WordsGmestoneFirstSendD_png":{"x":724,"y":726,"w":109,"h":77,"offX":0,"offY":0,"sourceW":109,"sourceH":77},
"ui_mall_WordsGmestoneFirstSendDNew_png":{"x":431,"y":713,"w":103,"h":72,"offX":3,"offY":2,"sourceW":109,"sourceH":77},
"ui_mall_WordsGmestoneFirstSendE_png":{"x":724,"y":805,"w":109,"h":77,"offX":0,"offY":0,"sourceW":109,"sourceH":77},
"ui_mall_WordsGmestoneFirstSendF_png":{"x":835,"y":765,"w":108,"h":76,"offX":0,"offY":1,"sourceW":109,"sourceH":77},
"ui_mall_WordsGmstoneFirstDouble_png":{"x":1,"y":787,"w":85,"h":85,"offX":0,"offY":0,"sourceW":85,"sourceH":85},
"ui_mall_WordsLingqu_png":{"x":875,"y":523,"w":135,"h":82,"offX":0,"offY":0,"sourceW":136,"sourceH":82}}}