{"width":256,"imagePath":"wj_000_palisitong_bs1_tex.png","height":256,"name":"wj_000_palisitong_bs1","SubTexture":[{"width":10,"y":154,"height":10,"name":"wj_000_palisitong_bs1_pz","x":149},{"frameHeight":25,"y":54,"frameX":-1,"width":17,"frameY":-1,"height":23,"name":"Pb_Hand_L","frameWidth":19,"x":180},{"frameHeight":30,"y":32,"frameX":-1,"width":14,"frameY":-1,"height":28,"name":"Dj_Hand_L","frameWidth":16,"x":164},{"width":20,"y":154,"height":53,"name":"Dj_UpArm_L","x":127},{"frameHeight":36,"y":167,"frameX":0,"width":20,"frameY":0,"height":35,"name":"Dj_Arm_L","frameWidth":20,"x":180},{"frameHeight":67,"y":49,"frameX":0,"width":22,"frameY":-1,"height":65,"name":"Dj_Leg_L","frameWidth":24,"x":140},{"frameHeight":20,"y":236,"frameX":-1,"width":33,"frameY":-1,"height":19,"name":"Dj_Foot_L","frameWidth":36,"x":166},{"frameHeight":69,"y":162,"frameX":-1,"width":26,"frameY":-1,"height":68,"name":"Dj_Thigh_L","frameWidth":27,"x":99},{"frameHeight":70,"y":49,"frameX":-1,"width":21,"frameY":-1,"height":69,"name":"Dj_Leg_R","frameWidth":22,"x":117},{"frameHeight":24,"y":209,"frameX":0,"width":37,"frameY":-1,"height":23,"name":"Dj_Foot_R","frameWidth":38,"x":207},{"width":27,"y":94,"height":66,"name":"Dj_Thigh_R","x":87},{"width":66,"y":1,"height":119,"name":"Dj_Body","x":1},{"frameHeight":51,"y":116,"frameX":0,"width":28,"frameY":-1,"height":49,"name":"Dj_UpArm_R","frameWidth":29,"x":163},{"frameHeight":39,"y":1,"frameX":-1,"width":18,"frameY":-1,"height":37,"name":"Dj_hua2","frameWidth":20,"x":118},{"frameHeight":18,"y":1,"frameX":-1,"width":26,"frameY":-1,"height":16,"name":"Pb_Hand_R","frameWidth":28,"x":205},{"frameHeight":22,"y":167,"frameX":-1,"width":35,"frameY":-1,"height":20,"name":"Dj_Hand_R","frameWidth":37,"x":202},{"frameHeight":21,"y":234,"frameX":0,"width":38,"frameY":-1,"height":20,"name":"Dj_Arm_R","frameWidth":39,"x":207},{"frameHeight":71,"y":122,"frameX":-1,"width":84,"frameY":0,"height":71,"name":"Dj_Head","frameWidth":85,"x":1},{"width":32,"y":189,"height":16,"name":"Dj_Eyes","x":202},{"frameHeight":27,"y":167,"frameX":-1,"width":29,"frameY":-1,"height":25,"name":"Dj_Hair08","frameWidth":31,"x":149},{"frameHeight":31,"y":209,"frameX":-1,"width":37,"frameY":-1,"height":29,"name":"Dj_Hair07","frameWidth":39,"x":127},{"frameHeight":15,"y":194,"frameX":-1,"width":29,"frameY":-1,"height":13,"name":"Dj_Hair06","frameWidth":31,"x":149},{"frameHeight":21,"y":28,"frameX":-1,"width":22,"frameY":-1,"height":19,"name":"Dj_Hair05","frameWidth":24,"x":138},{"frameHeight":31,"y":1,"frameX":-1,"width":18,"frameY":-1,"height":29,"name":"Dj_Hair04","frameWidth":20,"x":163},{"frameHeight":30,"y":1,"frameX":-1,"width":16,"frameY":-1,"height":28,"name":"Dj_Hair03","frameWidth":18,"x":239},{"frameHeight":34,"y":120,"frameX":-1,"width":45,"frameY":-1,"height":32,"name":"Dj_Hair01","frameWidth":47,"x":116},{"width":20,"y":1,"height":22,"name":"daqiao_huaban1","x":183},{"width":39,"y":209,"height":25,"name":"daqiao_huaban2","x":166},{"width":21,"y":31,"height":21,"name":"daqiao_huaban3","x":183},{"width":26,"y":232,"height":23,"name":"daqiao_huaban4","x":99},{"width":23,"y":1,"height":25,"name":"daqiao_huaban5","x":138},{"frameHeight":86,"y":49,"frameX":-14,"width":46,"frameY":-23,"height":43,"name":"xingxing","frameWidth":81,"x":69},{"width":47,"y":195,"height":46,"name":"buff_flo","x":1},{"width":47,"y":1,"height":46,"name":"buff_mid","x":69},{"width":47,"y":195,"height":46,"name":"buff_up","x":50}]}